koi_mcp/__init__.py
koi_mcp/__main__.py
koi_mcp/koi_mcp_server.py
koi_mcp/openapi.json
koi_mcp-0.1.4.dist-info/METADATA
koi_mcp-0.1.4.dist-info/WHEEL
koi_mcp-0.1.4.dist-info/entry_points.txt
koi_mcp-0.1.4.dist-info/licenses/LICENSE
koi_mcp-0.1.4.dist-info/RECORD
