Metadata-Version: 2.4
Name: koi-mcp
Version: 0.1.4
Summary: KOI Security MCP Server
License-File: LICENSE
Requires-Python: >=3.10
Requires-Dist: fastmcp>=2.10.0
Requires-Dist: httpx>=0.27
